{
  "en": "English",
  "zh": "中文",
  "Documentation": "Documentation",
  "Get Started": "Get Started",
  "Logout": "Logout",
  "Login with GitHub": "Login with GitHub",
  "Create": "Create",
  "Delete": "Delete",
  "Edit": "Edit",
  "Submit": "Submit",
  "Save": "Save",
  "Cancel": "Cancel",
  "Repository": "Repository",
  "Repository name": "Repository name",
  "Branch": "Branch",
  "Home": "Home",
  "Menu": "Menu",
  "Back to menu": "Back to menu",
  "Owner": "Owner",
  "Something went wrong": "Something went wrong, please try again later.",
  "Base path": "Base path",
  "File type": "File type",
  "File structure": "File structure",
  "Language": "Language",
  "Languages": "Languages",
  "Default language": "Default language",
  "Namespaces": "Namespaces",
  "Namespace": "Namespace",
  "Setup repo alert": "If your repository is not created by i18n-cms, please make sure you have already set up your existing repository.",
  "This website uses cookies to improve user experience": "This website uses cookies to improve user experience",
  "Learn more": "Learn more",
  "Accept": "Accept"
}